corelibrary/__init__.py
corelibrary/analytics/__init__.py
corelibrary/analytics/masterscale.py
corelibrary/analytics/model/__init__.py
corelibrary/analytics/model/scenario.py
corelibrary/analytics/model/factormodel/__init__.py
corelibrary/analytics/model/factormodel/basefactormodel.py
corelibrary/analytics/model/factormodel/yieldcurve.py
corelibrary/analytics/model/indexmodel/__init__.py
corelibrary/analytics/model/indexmodel/assetindexmodel.py
corelibrary/analytics/model/indexmodel/baseindexmodel.py
corelibrary/analytics/model/indexmodel/creditindexmodel.py
corelibrary/analytics/model/indexmodel/fxindexmodel.py
corelibrary/analytics/model/indexmodel/rateindexmodel.py
corelibrary/analytics/model/indexmodel/swaprateindexmodel.py
corelibrary/analytics/parameter/__init__.py
corelibrary/analytics/parameter/defaultcurve.py
corelibrary/analytics/parameter/dependent.py
corelibrary/analytics/parameter/fxcurve.py
corelibrary/analytics/parameter/spot.py
corelibrary/analytics/parameter/yieldcurve.py
corelibrary/analytics/parameter/vol/__init__.py
corelibrary/analytics/parameter/vol/assetvol.py
corelibrary/analytics/parameter/vol/basevol.py
corelibrary/analytics/parameter/vol/fxvol.py
corelibrary/analytics/parameter/vol/ratevol.py
corelibrary/analytics/result/__init__.py
corelibrary/analytics/result/detailstables.py
corelibrary/analytics/result/result.py
corelibrary/analytics/result/table.py
corelibrary/base/__init__.py
corelibrary/base/baseobject.py
corelibrary/base/ranger.py
corelibrary/base/interface/__init__.py
corelibrary/base/interface/credit.py
corelibrary/base/interface/defaultcurve.py
corelibrary/base/interface/effectiverate.py
corelibrary/base/interface/fairerate.py
corelibrary/base/interface/fxcurve.py
corelibrary/base/interface/index.py
corelibrary/base/interface/indexmodel.py
corelibrary/base/interface/masterscale.py
corelibrary/base/interface/payoff.py
corelibrary/base/interface/price.py
corelibrary/base/interface/pricing.py
corelibrary-0.1.1.dist-info/LICENSE
corelibrary-0.1.1.dist-info/METADATA
corelibrary-0.1.1.dist-info/WHEEL
corelibrary-0.1.1.dist-info/top_level.txt
corelibrary-0.1.1.dist-info/RECORD
