Metadata-Version: 2.1
Name: corelibrary
Version: 0.1.1
Summary: A core financial risk analytics library.
Home-page: https://github.com/pbrisk/corelibrary
Author: pbrisk, based on a fork of Deutsche Postbank [pbrisk]
Author-email: pbrisk_at_github@icloud.com
License: European Union Public Licence 1.1
Platform: any
Classifier: Development Status :: 3 - Alpha
Classifier: Intended Audience :: Developers
Classifier: Intended Audience :: Education
Classifier: Intended Audience :: Financial and Insurance Industry
Classifier: License :: OSI Approved :: Apache Software License
Classifier: Operating System :: OS Independent
Classifier: Programming Language :: Python
Classifier: Programming Language :: Python :: 2
Classifier: Programming Language :: Python :: 2.6
Classifier: Programming Language :: Python :: 2.7
Classifier: Topic :: Education
Classifier: Topic :: Office/Business
Classifier: Topic :: Office/Business :: Financial
Classifier: Topic :: Scientific/Engineering
Classifier: Topic :: Scientific/Engineering :: Mathematics
Classifier: Topic :: Utilities
Classifier: Topic :: Software Development :: Libraries :: Python Modules
Requires-Dist: unicum (==0.2)
Requires-Dist: goma (==0.1)
Requires-Dist: mitschreiben (==0.2)
Requires-Dist: businessdate (==0.4)
Requires-Dist: dcf (==0.2)
Requires-Dist: mathtoolspy (==0.2)
Requires-Dist: putcall (==0.1)
Requires-Dist: timewave (==0.5)
Requires-Dist: shortrate (==0.2)
Requires-Dist: numpy
Requires-Dist: scipy
